RJ23001UNO/__init__.py
RJ23001UNO/metodos.py
rj23001uno-1.0.0.dist-info/METADATA
rj23001uno-1.0.0.dist-info/WHEEL
rj23001uno-1.0.0.dist-info/top_level.txt
rj23001uno-1.0.0.dist-info/RECORD
