Metadata-Version: 2.4
Name: RJ23001UNO
Version: 1.0.0
Summary: Una librería para resolver sistemas de ecuaciones lineales y no lineales. Usando los métodos de: Eliminación de Gauss, Gauss-Jordan, Crammer, Jacobi, Gauss-Seidel, Bisección
Home-page: https://github.com/srnjdev/RJ23001UNO
Author: Sergio Ramírez
Author-email: rj23001@ues.edu.sv
Classifier: Programming Language :: Python :: 3
Classifier: License :: OSI Approved :: MIT License
Classifier: Operating System :: OS Independent
Requires-Python: >=3.6
Dynamic: author
Dynamic: author-email
Dynamic: classifier
Dynamic: description
Dynamic: description-content-type
Dynamic: home-page
Dynamic: requires-python
Dynamic: summary
